pytest_ordered.py
pytest_ordered-1.0.1.dist-info/licenses/LICENSE
pytest_ordered-1.0.1.dist-info/METADATA
pytest_ordered-1.0.1.dist-info/WHEEL
pytest_ordered-1.0.1.dist-info/entry_points.txt
pytest_ordered-1.0.1.dist-info/top_level.txt
pytest_ordered-1.0.1.dist-info/RECORD
